README.md
setup.cfg
setup.py
PyAcryl.egg-info/PKG-INFO
PyAcryl.egg-info/SOURCES.txt
PyAcryl.egg-info/dependency_links.txt
PyAcryl.egg-info/requires.txt
PyAcryl.egg-info/top_level.txt
pyacryl/__init__.py
pyacryl/address.py
pyacryl/asset.py
pyacryl/crypto.py
pyacryl/order.py