Metadata-Version: 1.0
Name: PyAcryl
Version: 0.1.3
Summary: Object-oriented library for the Acryl blockchain platform
Home-page: https://github.com/acrylplatform/PyAcryl
Author: PyAcryl
Author-email: dp@theinvaders.pro
License: MIT
Keywords: acryl,blockchain,analytics,crypto
Platform: UNKNOWN
